[{"id":"geonames:625144","name":"Minsk","aliases":["Minsk","MSQ","Mins'k","Minsc","Minscum","Minsk osh","Minska","Minskaj","Minskas","Minsko","Minszk","Mińsk","Myensk","Myenyesk","Mînsk","ming si ke","ming si ke shi","minseukeu","minsuku","min‍s‍ka","mnsk","mynsk","mynsq","mynysky","Μινσκ","Минск","Минск ош","Минскай","Мінск","Мінськ","Мѣньскъ","Մինսկ","מינסק","منسک","مىنىسكى","مينسك","مینسک","मिन्‍स्‍क","மின்ஸ்க்","ಮಿನ್ಸ್ಕ್","മിൻസ്ക്","มินสก์","མིན་སིཀ།","მინსკი","ミンスク","明斯克","明斯克市","민스크"],"population":1742124},{"id":"geonames:627907","name":"Homyel'","aliases":["Homyel'","GME","Gomel","Gomel'","Gomela","Gomelis","Gomelj","Gomeļa","Gómel","Homel","Homel'","Homelj","Homeľ","Homiel","Homyel","Homyel’","Hòmiel","ge mei li","ghwmyl","gomeል","gwml","gwmyl","homeri","hwml","komel","kx mel","Γόμελ","Гомел","Гомель","Гомељ","Гомєль","הומל","غوميل","ګwml","ګومل","گومل","گوميل","गोमेल","গোমেল","ਗੋਮੇਲ","கோமெல்","กอเมล","ጎሜል","ホメリ","戈梅利","호멜"],"population":501193},{"id":"geonames:627904","name":"Hrodna","aliases":["Hrodna","GNA","Gardinas","Garodnja","Goradnia","Grodna","Grodno","Grodņa","furodona","ge luo de nuo","ghrwdnw","grodano","grwdna","grwdnw","grwڈnw","grwډnw","heulodeuna","hwrdnh","krxd no","Гародня","Гродна","Гродно","הורדנה","غرودنو","گرودنا","گرودنو","گروڈنو","گروډنو","ग्रोडनो","গ্রোডনো","ਗ੍ਰੋਡਨੋ","กรอดโน","ግrodino","ግሮድኖ","フロドナ","格罗德诺","흐로드나"],"population":363718},{"id":"geonames:620127","name":"Vitebsk","aliases":["Vitebsk","VTB","Vicebsk","Vicebsko","Vicebszk","Viciebsk","Vit'b'sku","Vitebs'k","Vitebscum","Vitebska","Vitebskas","Vitepsk","Vitsebsk","Vitsemp'sk","Vitsiebsk","Vitsyebsk","Vítebsk","Vítsiebsk","Witebsk","Wizebsk","bhitebaska","bichebseukeu","fytybsk","vitebasaka","vitebaska","vitebisiki","vuitsuepusuku","wei jie bu si ke","wi tebskh","wtybsk","wytbsk","wytbsq","wyٹbsk","Βιτσέμπσκ","Витебск","Витепск","Витьбьскъ","Вітебськ","Віцебск","Վիտեբսկ","וויטעבסק","ויטבסק","فيتيبسك","وتیبسک","ویتبسک","ویٹبسک","विटेबस्क","ভিটেবস্ক","ਵਿਟੇਬਸਕ","วีเต็บสค์","ვიტებსკი","ቪቴብስክ","ヴィーツェプスク","维捷布斯克","비쳅스크"],"population":358927},{"id":"geonames:625665","name":"Mahilyow","aliases":["Mahilyow","MVQ","Magiljou","Maguilov","Mahileu","Mahiliou","Mahilioŭ","Mahiljou","Mahiljov","Mahiljow","Mahiljoŭ","Mahilou","Mahiloŭ","Mahilëŭ","Mogil'ov","Mogilev","Mogileva","Mogilew","Mogiliavas","Mogiliovas","Mogiljov","Mogiljow","Mogilov","Mogilëv","Mogiļeva","Moguilev","Mohylew","Məgilev","mogilebha","mogiliva","mogiryofu","moግilev","mwghylyf","mwgylb","mwgylf","mwgylyf","mwhylb","mʼhlyb","Магілёў","Могилев","Могильов","Могилёв","Могиљов","Мәгилев","מאהליב","מוגילב","מוהילב","موغيليف","موگیلف","موگیلیف","मोगिलेव","মোগিলেভ","ਮੋਗਿਲਿਵ","ሞግილev","モギリョフ"],"population":352896},{"id":"geonames:629634","name":"Brest","aliases":["Brest","BQT","Beras'ce","Berestja","Brehst","Bressicia","Brest Litovsk","Brest i Kviterussland","Brest nad Bugem","Brest-Litovsk","Brest-Litowsk","Bresta","Brestas","Bresto","Breszt","Brzesc","Brzesc nad Bugiem","Brzesc-Litewsk","Brzesc-Litewski","Brześć","Brześć nad Bugiem","Brześć-Litewsk","Brześć-Litewski","Brėst","Byeras'tsye","Byeras’tsye","be rst","beuleseuteu","biresiti","braisata","brst","brst  blarws","brysq","brysټ","bu lie si te","buresuto","Берасьце","Берестя","Брест","Брест-Литовск","Брэст","בריסק","ברסט","برست","برست، بلاروس","بریسٹ، بیلاروس","بریسټ","ब्रेस्ट","ब्रेस्त","ব্রেস্ট","ਬ੍ਰੈਸਟ","เบรสต์","ბრესტი","ብረስት","ブレスト","布列斯特","브레스트"],"population":347138},{"id":"geonames:630468","name":"Bobruysk","aliases":["Bobruysk","Babroejsk","Babruisk","Babrujsk","Babruysk","Bobruisk","Bobruiskas","Bobrujsk","bwbrwysq","Бoбруйск","Бабруйск","Бабрујск","Бобруйск","בוברויסק"],"population":205502},{"id":"geonames:630429","name":"Baranovichi","aliases":["Baranovichi","Baranavichy","Baranavitsjy","Baranawitschy","Baranoviche","Baranovichi - Baranavichy","Baranoviciai","Baranovitchi","Baranovitsi","Baranovitši","Baranovičiai","Baranowicze","Baranowitschi","Баранавічы","Барановичи"],"population":170039},{"id":"geonames:630376","name":"Barysaw","aliases":["Barysaw","Barysau","Borisov","Borissow","Horad Barysaw","Барысаў","Борисов"],"population":133700},{"id":"geonames:623549","name":"Pinsk","aliases":["Pinsk","Pins'k","Pinscum","Pinska","Pinskas","Pinszk","Pińsk","ping si ke","pinseukeu","pinsuku","pynsq","Пинск","Пінск","Пінськ","פינסק","ピンスク","平斯克","핀스크"],"population":123283},{"id":"geonames:625324","name":"Mazyr","aliases":["Mazyr","Masyr","Mazir","Mazira","Mozir","Mozyr","Mozyr'","Mozyrius","Mozyrz","Mozyr’","majileu","mazuiru","mo ji li","moziri","Мазыр","Мозир","Мозырь","מאזיר","მოზირი","マズィル","莫济里","마지르"],"population":104517},{"id":"geonames:626081","name":"Lida","aliases":["Lida","Lieda","Lyda","li da","rida","Ļida","Лида","Ліда","לידא","ليدا","ლიდა","リダ","利达","리다"],"population":103262},{"id":"geonames:624079","name":"Orsha","aliases":["Orsha","Orsa","Orscha","Orsza","Orŝa","Orša","TXC","Vorsja","ao er sha","boleusya","vuorusha","Орша","ヴォルシャ","奥尔沙","보르샤"],"population":101662},{"id":"geonames:622428","name":"Soligorsk","aliases":["Soligorsk","Chizhevichi","Saligorsk","Salihorsk","Salihorska","Salihorskas","Salyhorsk","Saļihorska","Soligors'k","Szalihorszk","salliholeuseukeu","salyhwrsk","suo li ge er si ke","Салигорск","Салігорск","Солигорск","Солігорськ","سالیهورسک","索利戈尔斯克","살리호르스크"],"population":96418},{"id":"geonames:624784","name":"Novopolotsk","aliases":["Novopolotsk","Navapolack","Navapolackas","Navapolatsk","Navapołack","Navapólatsk","Nawapolazk","Novopoloc'k","Novopolock","Novopolocka","Nowopolock","Nowopołock","Polotskiy","nabapollacheukeu","nwfwbwlwtsk","xin bo luo ci ke","Наваполацк","Новополоцк","Новополоцьк","نوفوبولوتسك","新波洛茨克","나바폴라츠크"],"population":95370},{"id":"geonames:625625","name":"Maladziečna","aliases":["Maladziečna","Maladziecna","Maladsetschna","Maladzechna","Maladzyechna","Molodechno","Molodeczno","Маладзечна","Молодечно"],"population":87339},{"id":"geonames:623317","name":"Polotsk","aliases":["Polotsk","Podolsk","Polack","Polatsk","Polazk","Poloc'k","Polock","Polocka","Polockas","Polot'sku","Polotia","Polotk","Polozk","Poloțk","Potolsk","Połack","Połock","Pòlatsk","Pólatsk","bo luo ci ke","pollacheukeu","poratsuku","Полацк","Полотьскъ","Полоцк","Полоцьк","Պոլոցկ","פולאצק","პოლოცკი","ポラツク","波洛茨克","폴라츠크"],"population":79285},{"id":"geonames:618806","name":"Zhlobin","aliases":["Zhlobin","Korpilovka","Zlobin","Жлобин","Жлобін"],"population":76304},{"id":"geonames:622794","name":"Rechytsa","aliases":["Rechytsa","Rechica","Rechitsa","Rechysta","Rehchyca","Retschyza","Ryechitsa","Речица","Рэчыца"],"population":64733},{"id":"geonames:618800","name":"Horad Zhodzina","aliases":["Horad Zhodzina","Gorad Zhodzina","Gorod Zhodino","Schodsina","Zhodino","Zhodzina","Zodino","Żodino","Горад Жодзіна","Жодзiна","Жодино"],"population":62983},{"id":"geonames:621074","name":"Svetlogorsk","aliases":["Svetlogorsk","Shatilki","Shatsilki","Svetlagorsk","Svyetlahorsk","Светлагорск","Светлогорск"],"population":61812},{"id":"geonames:621741","name":"Slutsk","aliases":["Slutsk","Sloetsk","Sloutsk","Sluc'k","Sluck","Slucka","Sluckas","Sluzk","Słuck","seullucheukeu","si lu ci ke","slutskh","slwzq","suutsuku","Слуцк","Слуцьк","סלוצק","สลูตสค์","スウツク","斯盧茨克","슬루츠크"],"population":58995},{"id":"geonames:627145","name":"Kobryn","aliases":["Kobryn","Kobrin","Kobrin'","Kobrina","Kobriny","Kobrynas","Kobryń","Kóbriny","ke bu lin","koburuin","qwbryn","Кобрин","Кобринь","Кобрын","קאברין","קוברין","コブルィン","科布林"],"population":52235},{"id":"geonames:621754","name":"Slonim","aliases":["Slonim","Slanimas","Slonima","Sloņima","Słonim","seullonim","si luo ni mu","slonimi","slwnym","suronimu","Слоним","Слонім","סלאנים","סלונים","სლონიმი","スロニム","斯洛尼姆","슬로님"],"population":48402},{"id":"geonames:620391","name":"Vaukavysk","aliases":["Vaukavysk","Valkaviskas","Vaukavisk","Vavkavisk","Vavkaviska","Vavkaviszk","Vawkavysk","Vaŭkavisk","Vaŭkavysk","Volkovisk","Volkovysk","Vovkovis'k","Waukawysk","Wolkowysk","Wołkowysk","fawkafysk","vuaukavuisuku","wa fu ka wei si ke","wawkwysk","wwlqwbysq","Вавкависк","Ваўкавыск","Вовковиськ","Волковиск","Волковыск","וואלקאוויסק","וולקוביסק","فاوكافيسك","واوکویسک","ヴァウカヴィスク","瓦夫卡維斯克"],"population":41020},{"id":"geonames:627751","name":"Kalinkovichi","aliases":["Kalinkovichi","Kalinkavichy","Kalinkowitschi","Калинкавичы","Калинковичи"],"population":36656},{"id":"geonames:621713","name":"Smarhoń","aliases":["Smarhoń","Smarhon","Smargon'","Smarhon'","Smarhon’","Smorgon'","Smorgone","Smorgonie","Smorgon’","Smurgainys","Смаргонь","Сморгонь"],"population":35072},{"id":"geonames:622739","name":"Rahachow","aliases":["Rahachow","Ragachou","Ragachov","Rahacou","Rahacovas","Rahatchow","Rahatjou","Rahatjoŭ","Rahatschou","Rahatsou","Rahatšou","Rahaĉoŭ","Rahačovas","Rahačoŭ","Rogachev","Rogachjov","Rogachov","Rogachëv","Rogatschew","Rohaczow","Rohaczów","luo jia qiao fu","rahachou","rhzwb","Рагачов","Рагачоў","Рогачëв","Рогачев","Рогачов","Рогачёв","ראגאטשאוו","רהצוב","ラハチョウ","羅加喬夫"],"population":31490},{"id":"geonames:628634","name":"Dzyarzhynsk","aliases":["Dzyarzhynsk","Dsjarschynsk","Dzerjinsk","Dzerzhins'k","Dzerzhinsk","Dzerĵinsk","Dziarjynsk","Dziarzjynsk","Dziarzynsk","Dziarzynskas","Dziaržynsk","Dziaržynskas","Dzierzynsk","Dzierżyńsk","Dzjarzhinsk","Dzjarzhynsk","Dzjarzinska","Dzjarzsinszk","Dzjarzynsk","Dzjaržinska","Dzjaržynsk","Kaiden","Kaydanovo","Koydanava","Koydanovo","dzyarjynsk","jie er ren si ke","Дзержинск","Дзержинськ","Дзяржынск","Дзјаржинск","دزيارجينسك","捷爾任斯克"],"population":29607},{"id":"geonames:624034","name":"Osipovichi","aliases":["Osipovichi","Asipopovichy","Asipovichy","Ospipovichi","Ossipowitschi","Sipovichi","Асіпоповічы","Осиповичи"],"population":28745},{"id":"geonames:627905","name":"Horki","aliases":["Horki","Gorki","Horkai","ge er ji","hwrky","hwrqy","Горки","Горкі","הורקי","هوركي","戈爾基"],"population":28626},{"id":"geonames:629454","name":"Byaroza","aliases":["Byaroza","Bereza","Bereza Kartuska","Bereza-Kartuskaya","Bereza-Kartuzskaya","Berjoza","Berëza","Bjaroza","Kartuz-Bereza","Берёза","Бяроза"],"population":27986},{"id":"geonames:624785","name":"Novogrudok","aliases":["Novogrudok","Naugardukas","Navagrudak","Navahradak","Navahroedak","Navahroudak","Navahrudak","Navahrudaka","Nawahradak","Novogrodek","Novogroudok","Novogrudek","Nowogrodek","Nowogródek","nabaheuludakeu","navuafurudaku","nbhrdq","xin ge lu duo ke","Навагрудак","Новогрудок","נבהרדק","ナヴァフルダク","新格鲁多克","나바흐루다크"],"population":27624},{"id":"geonames:620181","name":"Vileyka","aliases":["Vileyka","Vileika","Vilejka","Vilyeyka","Wilejka","Вилейка","Вілейка"],"population":26015},{"id":"geonames:621729","name":"Smaliavičy","aliases":["Smaliavičy","Smaliavicy","Gorad Smaljavichy","Horad Smalyavichy","Smalyavichy","Smolevichi","Smolewitsch","Горад Смалявічы","Смолевичи"],"population":24402},{"id":"geonames:625818","name":"Luninyets","aliases":["Luninyets","Luninec","Luninets","Luniniec","Luniniez","Łuniniec","Лунинец","Лунінец"],"population":23396},{"id":"geonames:626450","name":"Krychaw","aliases":["Krychaw","Krichev","Krychau","Krytchev","Krytschau","Кричев","Крычаў"],"population":22973},{"id":"geonames:627800","name":"Ivatsevichi","aliases":["Ivatsevichi","Fol'vark Ivatseviche","Fol’vark Ivatseviche","Ivacehvichy","Ivacevichi","Ivantsevichi","Ivatsevichy","Iwacewicze","Twacewicze","Івацэвічы","Ивацевичи"],"population":22189},{"id":"geonames:625409","name":"Mar’ina Gorka","aliases":["Mar’ina Gorka","Mar'ina Gorka","Mar''ina Horka","Maryina Gorka","Mar’’ina Horka","Марьина Горка","Мар’іна Горка"],"population":19892},{"id":"geonames:6846555","name":"Fanipol","aliases":["Fanipol","Fanipal","Fanipal'","Fanipalis","Fanipaĺ","Fanipol'","Фанiпаль","Фаниполь"],"population":19006},{"id":"geonames:622997","name":"Pruzhany","aliases":["Pruzhany","Pruzana","Pruzhana","Пружаны"],"population":18994},{"id":"geonames:623760","name":"Pastavy","aliases":["Pastavy","Pastavi","Pastawy","Pastovys","Pasztavi","Postavi","Postavy","Postawy","bo si ta wei","Пастави","Паставы","Постави","Поставы","פסטאווי","波斯塔維"],"population":18450},{"id":"geonames:629018","name":"Dobrush","aliases":["Dobrush","Добруш"],"population":17901},{"id":"geonames:627908","name":"Hlybokaye","aliases":["Hlybokaye","Glebokie","Glenboke","Glubokoe","Glubokoye","Glybokae","Glębokie","Глубокое","Глыбокае"],"population":17807},{"id":"geonames:621266","name":"Stowbtsy","aliases":["Stowbtsy","Stolbci","Stolbcy","Stolbtsy","Stolbtzy","Stolpcai","Stolpce","Stolptse","Stolptsy","Stolpze","Stoubcy","Stoubtsy","Stovbci","Stovpci","Stołpce","Stoŭbcy","Stoŭbtsy","Sztovbci","si tuo er bu qi","stwwbzy","stwypz","Стовпци","Столбци","Столбцы","Столбці","Стоўбцы","סטוובצי","סטויפץ","斯托爾布齊"],"population":17603},{"id":"geonames:625743","name":"Lyepyel’","aliases":["Lyepyel’","Lyepyel'","Lepel'","Lepel’","Лепель"],"population":17400},{"id":"geonames:619066","name":"Zaslawye","aliases":["Zaslawye","Saslauje","Zaslaue","Zaslauje","Zaslav","Zaslavje","Zaslavl'","Zaslavl’","Zaslavul","Zaslaw","Zaslaŭje","Zasław","Zasłaŭje","zasuraue","zha si la fu er","Заславль","Заславъл","Заславје","Заслаўе","זסלאוויה","ザスラーウエ","扎斯拉夫爾"],"population":17166},{"id":"geonames:627083","name":"Kalodzishchy","aliases":["Kalodzishchy","Kolodishchi","Kolodishhi","Калодзішчы","Колодищи"],"population":17000},{"id":"geonames:630515","name":"Oshmyany","aliases":["Oshmyany","Achmiany","Aschmjany","Ashmiany","Ashmjani","Ashmjany","Ashmyany","Asjmjany","Asmena","Asmiany","Asmjani","Asmjany","Ašmena","Ašmiany","Ašmjani","Ašmjany","Oshmjani","Oshmjany","Oshmyana","Oszmiana","ao shen mi ya nei","Ашмяны","Ашмјани","Ошмяни","Ошмяны","אשמיאני","奧什米亞內"],"population":16804},{"id":"geonames:629447","name":"Bykhov","aliases":["Bykhov","Bikhav","Bikhov","Bychau","Bychavas","Bychaŭ","Bychow","Bychów","Byh'au","Byh’au","Bykhau","Bykhaw","Star Bykhov","Staryy Bykhov","bei huo fu","bihapeu","bihau","byhwb","Бихав","Бихов","Быхаў","Быхов","ביחוב","ビハウ","貝霍夫","비하프"],"population":16296},{"id":"geonames:624700","name":"Nesvizh","aliases":["Nesvizh","Nes'vezh","Nesvyzius","Nesvyžius","Nes’vezh","Nieswiez","Nieśwież","Njasviz","Njasvizh","Njasviž","Njaswisch","Nyasvizh","Nyaszvizs","Несвиж","Нясвіж"],"population":15897},{"id":"geonames:627811","name":"Ivanovo","aliases":["Ivanovo","Ivanava","Janow","Janów","Yanov","Yanuv","Іванава","Иваново"],"population":15833},{"id":"geonames:618815","name":"Žytkavičy","aliases":["Žytkavičy","Zytkavicy","Jitkovichi","Jytkavitchy","Zhitkavichi","Zhitkovichi","Zhytkavichy","Zhytkavychy","Zjytkavytjy","Zytkavicai","Zytkavitsy","Zytkowicze","Żytkowicze","Žytkavitšy","Žytkavičai","Житкавичи","Житковичи","Житковичі","Жыткавычы","Жыткавічы"],"population":15788},{"id":"geonames:625972","name":"Logoysk","aliases":["Logoysk","Lagojsk","Lahoysk","Logojsk","Лагойск","Логойск"],"population":15543},{"id":"geonames:623941","name":"Astraviec","aliases":["Astraviec","Astravas","Astravec","Astravets","Astraviets","Astravjeca","Astravyets","Ostrov","Ostrovcy","Ostrovec","Ostrovec'","Ostrovets","Ostrowiec","ao si te luo wei ci","Астравец","Островец","Островець","Островцы","奧斯特羅韋茨"],"population":15265},{"id":"geonames:622113","name":"Shchuchyn","aliases":["Shchuchyn","Shchuchin","Shhuchin","Szczuczyn","Шчучын","Щучин"],"population":15127}]