[{"id":"geonames:921815","name":"Mamoudzou","aliases":["Mamoudzou","Mambutzou","Mamoutzou","Mamudzu","Mamutzu","mamuju","Мамудзу","마무주"],"population":54831},{"id":"geonames:1090225","name":"Koungou","aliases":["Koungou","Kongo","Kungu","kaungu","kongu","kwenigu","kwnghw","kwngw","kwnګw","Кунгу","كونغو","کونګو","کونگو","कौंगु","কোঙ্গু","ਕੌਂਗੂ","ኮንጉ","クングー"],"population":18118},{"id":"geonames:1090275","name":"Labattoir","aliases":["Labattoir"],"population":17739},{"id":"geonames:1090239","name":"Kaouéni","aliases":["Kaouéni","Kaoueni"],"population":17060},{"id":"geonames:1090242","name":"Mtsapéré","aliases":["Mtsapéré","Mtsapere"],"population":15880},{"id":"geonames:921900","name":"Dzaoudzi","aliases":["Dzaoudzi","DZA","Dzaoudzi-Labattoir","Dzaudzi","Zaudzi","daja'udaji","daza'udazi","dizaውdizi","dja'udaji","dzawdzy","zao de ji","zauji","Дзаудзи","دزاودزي","دزاودزی","ڈzawڈzy","ڈزاؤڈزی","ډzawdzy","ډزاودزی","ड्जाउडजी","ডজাউডজি","ਡਜ਼ਾਉਡਜ਼ੀ","ድዛውድዚ","ザウジ","藻德济"],"population":15339}]